{
  "version": "5",
  "dialect": "mysql",
  "id": "341d2afa-fa8b-4b2f-9a72-a8d93705f095",
  "prevId": "2ebcb80c-643a-4af6-88c0-06101084b109",
  "tables": {
    "chamados": {
      "name": "chamados",
      "columns": {
        "id": {
          "name": "id",
          "type": "int",
          "primaryKey": false,
          "notNull": true,
          "autoincrement": true
        },
        "numeroOS": {
          "name": "numeroOS",
          "type": "varchar(20)",
          "primaryKey": false,
          "notNull": true,
          "autoincrement": false
        },
        "numeroTarefa": {
          "name": "numeroTarefa",
          "type": "varchar(50)",
          "primaryKey": false,
          "notNull": false,
          "autoincrement": false
        },
        "dataOS": {
          "name": "dataOS",
          "type": "timestamp",
          "primaryKey": false,
          "notNull": true,
          "autoincrement": false
        },
        "dataAtendimento": {
          "name": "dataAtendimento",
          "type": "timestamp",
          "primaryKey": false,
          "notNull": false,
          "autoincrement": false
        },
        "distrito": {
          "name": "distrito",
          "type": "varchar(10)",
          "primaryKey": false,
          "notNull": false,
          "autoincrement": false
        },
        "nomeGT": {
          "name": "nomeGT",
          "type": "varchar(100)",
          "primaryKey": false,
          "notNull": false,
          "autoincrement": false
        },
        "codCliente": {
          "name": "codCliente",
          "type": "varchar(20)",
          "primaryKey": false,
          "notNull": false,
          "autoincrement": false
        },
        "cliente": {
          "name": "cliente",
          "type": "text",
          "primaryKey": false,
          "notNull": false,
          "autoincrement": false
        },
        "nomeTRA": {
          "name": "nomeTRA",
          "type": "varchar(100)",
          "primaryKey": false,
          "notNull": false,
          "autoincrement": false
        },
        "observacao": {
          "name": "observacao",
          "type": "text",
          "primaryKey": false,
          "notNull": false,
          "autoincrement": false
        },
        "status": {
          "name": "status",
          "type": "enum('aguardando_agendamento','agendado','ag_retorno','atendido_ag_fechamento','fechado')",
          "primaryKey": false,
          "notNull": true,
          "autoincrement": false,
          "default": "'aguardando_agendamento'"
        },
        "createdAt": {
          "name": "createdAt",
          "type": "timestamp",
          "primaryKey": false,
          "notNull": true,
          "autoincrement": false,
          "default": "(now())"
        },
        "updatedAt": {
          "name": "updatedAt",
          "type": "timestamp",
          "primaryKey": false,
          "notNull": true,
          "autoincrement": false,
          "onUpdate": true,
          "default": "(now())"
        },
        "createdBy": {
          "name": "createdBy",
          "type": "int",
          "primaryKey": false,
          "notNull": false,
          "autoincrement": false
        }
      },
      "indexes": {},
      "foreignKeys": {
        "chamados_createdBy_users_id_fk": {
          "name": "chamados_createdBy_users_id_fk",
          "tableFrom": "chamados",
          "tableTo": "users",
          "columnsFrom": [
            "createdBy"
          ],
          "columnsTo": [
            "id"
          ],
          "onDelete": "no action",
          "onUpdate": "no action"
        }
      },
      "compositePrimaryKeys": {
        "chamados_id": {
          "name": "chamados_id",
          "columns": [
            "id"
          ]
        }
      },
      "uniqueConstraints": {
        "chamados_numeroOS_unique": {
          "name": "chamados_numeroOS_unique",
          "columns": [
            "numeroOS"
          ]
        }
      },
      "checkConstraint": {}
    },
    "evolucoes": {
      "name": "evolucoes",
      "columns": {
        "id": {
          "name": "id",
          "type": "int",
          "primaryKey": false,
          "notNull": true,
          "autoincrement": true
        },
        "chamadoId": {
          "name": "chamadoId",
          "type": "int",
          "primaryKey": false,
          "notNull": true,
          "autoincrement": false
        },
        "descricao": {
          "name": "descricao",
          "type": "text",
          "primaryKey": false,
          "notNull": true,
          "autoincrement": false
        },
        "statusAnterior": {
          "name": "statusAnterior",
          "type": "enum('aberto','em_andamento','fechado')",
          "primaryKey": false,
          "notNull": false,
          "autoincrement": false
        },
        "statusNovo": {
          "name": "statusNovo",
          "type": "enum('aberto','em_andamento','fechado')",
          "primaryKey": false,
          "notNull": false,
          "autoincrement": false
        },
        "createdAt": {
          "name": "createdAt",
          "type": "timestamp",
          "primaryKey": false,
          "notNull": true,
          "autoincrement": false,
          "default": "(now())"
        },
        "createdBy": {
          "name": "createdBy",
          "type": "int",
          "primaryKey": false,
          "notNull": true,
          "autoincrement": false
        }
      },
      "indexes": {},
      "foreignKeys": {
        "evolucoes_chamadoId_chamados_id_fk": {
          "name": "evolucoes_chamadoId_chamados_id_fk",
          "tableFrom": "evolucoes",
          "tableTo": "chamados",
          "columnsFrom": [
            "chamadoId"
          ],
          "columnsTo": [
            "id"
          ],
          "onDelete": "cascade",
          "onUpdate": "no action"
        },
        "evolucoes_createdBy_users_id_fk": {
          "name": "evolucoes_createdBy_users_id_fk",
          "tableFrom": "evolucoes",
          "tableTo": "users",
          "columnsFrom": [
            "createdBy"
          ],
          "columnsTo": [
            "id"
          ],
          "onDelete": "no action",
          "onUpdate": "no action"
        }
      },
      "compositePrimaryKeys": {
        "evolucoes_id": {
          "name": "evolucoes_id",
          "columns": [
            "id"
          ]
        }
      },
      "uniqueConstraints": {},
      "checkConstraint": {}
    },
    "users": {
      "name": "users",
      "columns": {
        "id": {
          "name": "id",
          "type": "int",
          "primaryKey": false,
          "notNull": true,
          "autoincrement": true
        },
        "openId": {
          "name": "openId",
          "type": "varchar(64)",
          "primaryKey": false,
          "notNull": true,
          "autoincrement": false
        },
        "name": {
          "name": "name",
          "type": "text",
          "primaryKey": false,
          "notNull": false,
          "autoincrement": false
        },
        "email": {
          "name": "email",
          "type": "varchar(320)",
          "primaryKey": false,
          "notNull": false,
          "autoincrement": false
        },
        "loginMethod": {
          "name": "loginMethod",
          "type": "varchar(64)",
          "primaryKey": false,
          "notNull": false,
          "autoincrement": false
        },
        "role": {
          "name": "role",
          "type": "enum('user','admin')",
          "primaryKey": false,
          "notNull": true,
          "autoincrement": false,
          "default": "'user'"
        },
        "createdAt": {
          "name": "createdAt",
          "type": "timestamp",
          "primaryKey": false,
          "notNull": true,
          "autoincrement": false,
          "default": "(now())"
        },
        "updatedAt": {
          "name": "updatedAt",
          "type": "timestamp",
          "primaryKey": false,
          "notNull": true,
          "autoincrement": false,
          "onUpdate": true,
          "default": "(now())"
        },
        "lastSignedIn": {
          "name": "lastSignedIn",
          "type": "timestamp",
          "primaryKey": false,
          "notNull": true,
          "autoincrement": false,
          "default": "(now())"
        }
      },
      "indexes": {},
      "foreignKeys": {},
      "compositePrimaryKeys": {
        "users_id": {
          "name": "users_id",
          "columns": [
            "id"
          ]
        }
      },
      "uniqueConstraints": {
        "users_openId_unique": {
          "name": "users_openId_unique",
          "columns": [
            "openId"
          ]
        }
      },
      "checkConstraint": {}
    }
  },
  "views": {},
  "_meta": {
    "schemas": {},
    "tables": {},
    "columns": {}
  },
  "internal": {
    "tables": {},
    "indexes": {}
  }
}